AutoBET/BET.py
AutoBET/__init__.py
data/MNI152_T1.nii.gz
data/MNI152_mask.nii.gz
data/__init__.py
AutoBET-0.1.5.dist-info/LICENSE
AutoBET-0.1.5.dist-info/METADATA
AutoBET-0.1.5.dist-info/WHEEL
AutoBET-0.1.5.dist-info/top_level.txt
AutoBET-0.1.5.dist-info/RECORD
